release_finder/__init__.py
release_finder/github.py
release_finder/release.py
release_finder-0.1.0.dist-info/LICENSE
release_finder-0.1.0.dist-info/METADATA
release_finder-0.1.0.dist-info/WHEEL
release_finder-0.1.0.dist-info/RECORD
