Metadata-Version: 2.1
Name: release-finder
Version: 0.1.0
Summary: Python package that helps you find the latest releases information for a given GitHub repository.
Home-page: https://github.com/rahulXs/release-finder
License: MIT
Keywords: release-finder,release,finder,version,tag,rahulXs
Author: Rahul Sharma
Author-email: rahulxsh@gmail.com
Maintainer: Rahul Sharma
Maintainer-email: rahulxsh@gmail.com
Requires-Python: >=3.9,<4.0
Classifier: License :: OSI Approved :: MIT License
Classifier: Programming Language :: Python
Classifier: Programming Language :: Python :: 3
Classifier: Programming Language :: Python :: 3.9
Classifier: Programming Language :: Python :: 3.10
Classifier: Programming Language :: Python :: 3.11
Classifier: Programming Language :: Python :: 3
Requires-Dist: requests (>=2.13.0,<3.0.0)
Project-URL: Repository, https://github.com/rahulXs/release-finder
